outscraper_mcp_server/__init__.py
outscraper_mcp_server/__main__.py
outscraper_mcp_server/server.py
outscraper_mcp_server-0.1.2.dist-info/licenses/LICENSE
outscraper_mcp_server-0.1.2.dist-info/METADATA
outscraper_mcp_server-0.1.2.dist-info/WHEEL
outscraper_mcp_server-0.1.2.dist-info/entry_points.txt
outscraper_mcp_server-0.1.2.dist-info/top_level.txt
outscraper_mcp_server-0.1.2.dist-info/RECORD
