Metadata-Version: 2.4
Name: outscraper-mcp-server
Version: 0.1.2
Summary: MCP server exposing Outscraper tools
Author-email: Outscraper <developers@outscraper.com>
License-Expression: MIT
Project-URL: Homepage, https://github.com/outscraper/outscraper-mcp
Project-URL: Repository, https://github.com/outscraper/outscraper-mcp.git
Project-URL: Issues, https://github.com/outscraper/outscraper-mcp/issues
Project-URL: Documentation, https://github.com/outscraper/outscraper-mcp#readme
Project-URL: Bug Reports, https://github.com/outscraper/outscraper-mcp/issues
Project-URL: Source Code, https://github.com/outscraper/outscraper-mcp
Keywords: mcp,outscraper,google-maps,reviews,search,data-extraction,business-intelligence,api,google
Requires-Python: >=3.10
License-File: LICENSE
Requires-Dist: outscraper>=5.9.1
Requires-Dist: fastmcp>=2.8.0
Requires-Dist: python-dotenv>=1.1.0
Provides-Extra: dev
Requires-Dist: pytest>=7.0.0; extra == "dev"
Requires-Dist: pytest-asyncio>=0.21.0; extra == "dev"
Requires-Dist: black>=22.0.0; extra == "dev"
Requires-Dist: flake8>=4.0.0; extra == "dev"
Requires-Dist: mypy>=1.0.0; extra == "dev"
Requires-Dist: twine>=4.0.0; extra == "dev"
Requires-Dist: build>=0.10.0; extra == "dev"
Dynamic: license-file
